microstats.py
setup.cfg
setup.py
microstats.egg-info/PKG-INFO
microstats.egg-info/SOURCES.txt
microstats.egg-info/dependency_links.txt
microstats.egg-info/top_level.txt