Metadata-Version: 1.2
Name: microstats
Version: 0.1.1
Summary: A very simple in-memory statistics module.
Home-page: https://github.com/guyingbo/microstats
Author: Yingbo Gu
Author-email: tensiongyb@gmail.com
License: MIT
Platform: UNKNOWN
Classifier: Programming Language :: Python :: 2
Classifier: Programming Language :: Python :: 3
Classifier: Intended Audience :: Developers
Requires-Python: >=3.5
